{
  "name": "no-pipe-touching",
  "version": "1.1.12",
  "title": "No Pipe Touching 2.0",
  "description": "This mod alters existing pipes. You will need another mod to add new pipes.\nAllows you to place pipes of different materials next to each other without them connecting. Designed as a less fancy alternative to advanced fluid handling, without the recipe complexity of flow control.",
  "author": "protocol_1903",
  "factorio_version": "2.0",
  "dependencies": [
    "base >= 2.0.21",
    "? RGBPipes",
    "? color-coded-pipes >= 1.0.3",
    "? underground-pipe-pack >= 2.0.3",
    "? FluidMustFlow",
    "? Flow Control"
  ]
}